quik_db/__about__.py
quik_db/__init__.py
quik_db/core/__init__.py
quik_db/core/database.py
quik_db/core/debug.py
quik_db/core/handlers.py
quik_db/dictionaries/__init__.py
quik_db/dictionaries/db_errors.py
quik_db/dictionaries/model_errors.py
quik_db/dictionaries/model_fields.py
quik_db/dictionaries/resources.py
quik_db/model/__init__.py
quik_db/model/enums.py
quik_db/model/exceptions.py
quik_db/model/metadata.py
quik_db/model/models.py
quik_db/model/validator.py
quik_db/utils/__init__.py
quik_db/utils/db_utils.py
quik_db/utils/formatters.py
quik_db-0.1.21.dist-info/LICENSE.txt
quik_db-0.1.21.dist-info/METADATA
quik_db-0.1.21.dist-info/WHEEL
quik_db-0.1.21.dist-info/top_level.txt
quik_db-0.1.21.dist-info/RECORD
