Metadata-Version: 2.1
Name: quik_db
Version: 0.1.21
Summary: A python library for a streamlined database experience from config file
Author-email: Victor Nguyen <victor.win86@gmail.com>
License: MIT
Project-URL: homepage, https://github.com/hotnsoursoup/quik-db
Project-URL: documentation, https://github.com/hotnsoursoup/quik-db/tree/master/docs
Project-URL: testing, https://github.com/hotnsoursoup/quik-db/blob/master/docs/tests.md
Keywords: database,SQL,config,ORM,streamlined
Classifier: License :: OSI Approved :: MIT License
Classifier: Operating System :: OS Independent
Classifier: Programming Language :: Cython
Classifier: Programming Language :: Python
Classifier: Programming Language :: Python :: 3
Classifier: Programming Language :: Python :: 3 :: Only
Classifier: Programming Language :: Python :: 3.11
Classifier: Programming Language :: Python :: 3.12
Classifier: Programming Language :: Python :: 3.13
Classifier: Topic :: Database
Requires-Python: >=3.11
License-File: LICENSE.txt
Requires-Dist: pydantic>=2.9.1
Requires-Dist: SQLAlchemy>=2.0.34
Requires-Dist: sqlparse>=0.5.1
Requires-Dist: sqlglot>=25.29.0
Requires-Dist: python-dateutil>=2.8.2
Provides-Extra: mysql
Requires-Dist: pymysql; extra == "mysql"
Provides-Extra: mariadb
Requires-Dist: mariadb; extra == "mariadb"
Provides-Extra: postgresql
Requires-Dist: psycopg2>=2.9.6; extra == "postgresql"
Provides-Extra: mssql
Requires-Dist: pymssql>=2.2.0; extra == "mssql"
Provides-Extra: oracle
Requires-Dist: oracledb>=2.3.0; extra == "oracle"
Provides-Extra: all-dbs
Requires-Dist: pymysql; extra == "all-dbs"
Requires-Dist: psycopg2>=2.9.6; extra == "all-dbs"
Requires-Dist: pymssql>=2.2.2; extra == "all-dbs"
Requires-Dist: oracledb>=2.3.0; extra == "all-dbs"
Requires-Dist: mariadb; extra == "all-dbs"
Provides-Extra: dev
Requires-Dist: ruff; extra == "dev"
Requires-Dist: bandit; extra == "dev"
Requires-Dist: black; extra == "dev"
Requires-Dist: isort; extra == "dev"
Provides-Extra: test
Requires-Dist: pytest; extra == "test"
Requires-Dist: pytest-html; extra == "test"
Requires-Dist: pytest-order; extra == "test"
Requires-Dist: pyaml-env; extra == "test"
Provides-Extra: all
Requires-Dist: pymysql; extra == "all"
Requires-Dist: psycopg2>=2.9.6; extra == "all"
Requires-Dist: pymssql>=2.2.2; extra == "all"
Requires-Dist: oracledb>=2.3.0; extra == "all"
Requires-Dist: mariadb; extra == "all"
Requires-Dist: ruff; extra == "all"
Requires-Dist: bandit; extra == "all"
Requires-Dist: black; extra == "all"
Requires-Dist: isort; extra == "all"
Requires-Dist: pytest; extra == "all"
Requires-Dist: pytest-html; extra == "all"
Requires-Dist: pytest-order; extra == "all"
Requires-Dist: pyaml-env; extra == "all"
